apkparser/__init__.py
apkparser/main.py
apkparser/helper/__init__.py
apkparser/helper/logging.py
apkparser/permissions/__init__.py
apkparser/permissions/ressources/__init__.py
apkparser/permissions/ressources/aosp_permissions/permissions_10.json
apkparser/permissions/ressources/aosp_permissions/permissions_13.json
apkparser/permissions/ressources/aosp_permissions/permissions_14.json
apkparser/permissions/ressources/aosp_permissions/permissions_15.json
apkparser/permissions/ressources/aosp_permissions/permissions_16.json
apkparser/permissions/ressources/aosp_permissions/permissions_17.json
apkparser/permissions/ressources/aosp_permissions/permissions_18.json
apkparser/permissions/ressources/aosp_permissions/permissions_19.json
apkparser/permissions/ressources/aosp_permissions/permissions_21.json
apkparser/permissions/ressources/aosp_permissions/permissions_22.json
apkparser/permissions/ressources/aosp_permissions/permissions_23.json
apkparser/permissions/ressources/aosp_permissions/permissions_24.json
apkparser/permissions/ressources/aosp_permissions/permissions_25.json
apkparser/permissions/ressources/aosp_permissions/permissions_26.json
apkparser/permissions/ressources/aosp_permissions/permissions_27.json
apkparser/permissions/ressources/aosp_permissions/permissions_28.json
apkparser/permissions/ressources/aosp_permissions/permissions_29.json
apkparser/permissions/ressources/aosp_permissions/permissions_30.json
apkparser/permissions/ressources/aosp_permissions/permissions_31.json
apkparser/permissions/ressources/aosp_permissions/permissions_32.json
apkparser/permissions/ressources/aosp_permissions/permissions_33.json
apkparser/permissions/ressources/aosp_permissions/permissions_34.json
apkparser/permissions/ressources/aosp_permissions/permissions_35.json
apkparser/permissions/ressources/aosp_permissions/permissions_36.json
apkparser/permissions/ressources/aosp_permissions/permissions_4.json
apkparser/permissions/ressources/aosp_permissions/permissions_5.json
apkparser_ag-0.0.2.dist-info/licenses/LICENSE
apkparser_ag-0.0.2.dist-info/METADATA
apkparser_ag-0.0.2.dist-info/WHEEL
apkparser_ag-0.0.2.dist-info/entry_points.txt
apkparser_ag-0.0.2.dist-info/top_level.txt
apkparser_ag-0.0.2.dist-info/RECORD
