Metadata-Version: 2.4
Name: apkparser-ag
Version: 0.0.2
Summary: APK Parser: Your Crowbar for Android Archives
Author-email: anthony <ping@42.bzh>
License:                                  Apache License
Keywords: Android, Androguard, Security
Classifier: Development Status :: 4 - Beta
Classifier: License :: OSI Approved :: Apache Software License
Classifier: Programming Language :: Python
Classifier: Programming Language :: Python :: 3
Classifier: Programming Language :: Python :: 3 :: Only
Classifier: Programming Language :: Python :: 3.9
Classifier: Programming Language :: Python :: 3.10
Classifier: Programming Language :: Python :: 3.11
Classifier: Programming Language :: Python :: 3.12
Classifier: Programming Language :: Python :: 3.13
Classifier: Topic :: Security
Classifier: Topic :: Software Development
Classifier: Topic :: Utilities
Requires-Python: >=3.10
License-File: LICENSE
Requires-Dist: dex-parser>=0.0.1
Requires-Dist: axml>=0.0.2
Requires-Dist: rich>=14.0.0
Requires-Dist: asn1crypto>=1.5.1
Requires-Dist: cryptography>=45.0.7
Requires-Dist: python-magic>=0.4.27
Dynamic: license-file
